speedevo/__init__.py
speedevo/speedevo.py
speedevo-0.0.5.dist-info/LICENSE
speedevo-0.0.5.dist-info/METADATA
speedevo-0.0.5.dist-info/WHEEL
speedevo-0.0.5.dist-info/top_level.txt
speedevo-0.0.5.dist-info/RECORD
